paquete/__init__.py
el_paquete_de_barbi-0.0.1.dist-info/LICENSE
el_paquete_de_barbi-0.0.1.dist-info/METADATA
el_paquete_de_barbi-0.0.1.dist-info/WHEEL
el_paquete_de_barbi-0.0.1.dist-info/top_level.txt
el_paquete_de_barbi-0.0.1.dist-info/RECORD
