Metadata-Version: 2.1
Name: el-paquete-de-barbi
Version: 0.0.1
Summary: Un gran paquete
Home-page: https://github.com/barbiquilmes/test
Author: barbi_de_quilmes
Author-email: author@example.com
License: UNKNOWN
Platform: UNKNOWN
Classifier: Programming Language :: Python :: 3
Classifier: License :: OSI Approved :: MIT License
Classifier: Operating System :: OS Independent
